odoo/addons/website_sale_resource_booking/README.rst
odoo/addons/website_sale_resource_booking/__init__.py
odoo/addons/website_sale_resource_booking/__manifest__.py
odoo/addons/website_sale_resource_booking/controllers/__init__.py
odoo/addons/website_sale_resource_booking/controllers/main.py
odoo/addons/website_sale_resource_booking/data/ir_cron_data.xml
odoo/addons/website_sale_resource_booking/i18n/es.po
odoo/addons/website_sale_resource_booking/i18n/it.po
odoo/addons/website_sale_resource_booking/i18n/pt_BR.po
odoo/addons/website_sale_resource_booking/i18n/website_sale_resource_booking.pot
odoo/addons/website_sale_resource_booking/migrations/17.0.1.0.0/post-migration.py
odoo/addons/website_sale_resource_booking/models/__init__.py
odoo/addons/website_sale_resource_booking/models/product_template.py
odoo/addons/website_sale_resource_booking/models/resource_booking.py
odoo/addons/website_sale_resource_booking/models/sale_order.py
odoo/addons/website_sale_resource_booking/models/sale_order_line.py
odoo/addons/website_sale_resource_booking/models/website.py
odoo/addons/website_sale_resource_booking/readme/CONTRIBUTORS.md
odoo/addons/website_sale_resource_booking/readme/DESCRIPTION.md
odoo/addons/website_sale_resource_booking/readme/INSTALL.md
odoo/addons/website_sale_resource_booking/readme/USAGE.md
odoo/addons/website_sale_resource_booking/static/description/icon.png
odoo/addons/website_sale_resource_booking/static/description/index.html
odoo/addons/website_sale_resource_booking/static/tests/tours/tour.esm.js
odoo/addons/website_sale_resource_booking/templates/website_sale.xml
odoo/addons/website_sale_resource_booking/tests/__init__.py
odoo/addons/website_sale_resource_booking/tests/test_ui.py
odoo/addons/website_sale_resource_booking/views/product_template_view.xml
odoo_addon_website_sale_resource_booking-17.0.1.0.0.3.dist-info/METADATA
odoo_addon_website_sale_resource_booking-17.0.1.0.0.3.dist-info/WHEEL
odoo_addon_website_sale_resource_booking-17.0.1.0.0.3.dist-info/top_level.txt
odoo_addon_website_sale_resource_booking-17.0.1.0.0.3.dist-info/RECORD
